pyHydraulic/__init__.py
pyHydraulic/node_content_widget.py
pyHydraulic/node_edge.py
pyHydraulic/node_editor_widget.py
pyHydraulic/node_editor_window.py
pyHydraulic/node_graphics_cutline.py
pyHydraulic/node_graphics_edge.py
pyHydraulic/node_graphics_node.py
pyHydraulic/node_graphics_scene.py
pyHydraulic/node_graphics_socket.py
pyHydraulic/node_graphics_view.py
pyHydraulic/node_node.py
pyHydraulic/node_scene.py
pyHydraulic/node_scene_clipboard.py
pyHydraulic/node_scene_history.py
pyHydraulic/node_serializable.py
pyHydraulic/node_socket.py
pyHydraulic/utils.py
pyHydraulic/hydraulicSketcher/Tool.py
pyHydraulic/hydraulicSketcher/__init__.py
pyHydraulic/hydraulicSketcher/datasent.txt
pyHydraulic/hydraulicSketcher/hydraulicSketcher.py
pyHydraulic/hydraulicSketcher/icons_rc.py
pyHydraulic/hydraulicSketcher/mainWindow_ui.py
pyHydraulic/hydraulicSketcher/node_editor_window.py
pyHydraulic/hydraulicSketcher/sample.json
pyHydraulic/hydraulicSketcher/server.py
pyHydraulic/hydraulicSketcher/server_ui.py
pyHydraulic/hydraulicSketcher/skin.qss
pyHydraulic/hydraulicSketcher/test.json
pyHydraulic/hydraulicSketcher/testNew.json
pyHydraulic/hydraulicSketcher/images/APPIcon.png
pyHydraulic/hydraulicSketcher/images/accumulator.png
pyHydraulic/hydraulicSketcher/images/card.png
pyHydraulic/hydraulicSketcher/images/dataAcq.png
pyHydraulic/hydraulicSketcher/images/filter.png
pyHydraulic/hydraulicSketcher/images/flow meter.png
pyHydraulic/hydraulicSketcher/images/gauge.png
pyHydraulic/hydraulicSketcher/images/one-way valve.png
pyHydraulic/hydraulicSketcher/images/picture.png
pyHydraulic/hydraulicSketcher/images/piston dual.png
pyHydraulic/hydraulicSketcher/images/piston left.png
pyHydraulic/hydraulicSketcher/images/piston right.png
pyHydraulic/hydraulicSketcher/images/pressure sensor.png
pyHydraulic/hydraulicSketcher/images/pump.png
pyHydraulic/hydraulicSketcher/images/relief valve.png
pyHydraulic/hydraulicSketcher/images/servo valve.png
pyHydraulic/hydraulicSketcher/images/simple tank.png
pyHydraulic-1.1.7.dist-info/LICENCE
pyHydraulic-1.1.7.dist-info/METADATA
pyHydraulic-1.1.7.dist-info/WHEEL
pyHydraulic-1.1.7.dist-info/top_level.txt
pyHydraulic-1.1.7.dist-info/RECORD
